{
    "domande": [
        {
            "pattern": "ciao",
            "risposta": "Come posso aiutarti?",
            "argomento": "generale"
        },
        {
            "pattern": "(dimmi|raccontami|sai)\\s*una\\s*barzelletta",
            "risposte": [
                "Perch\u00e9 il pomodoro non riesce a dormire? Perch\u00e9 l'insalata russa!",
                "Qual \u00e8 il colmo per un elettricista? Non fare mai scintille con la moglie!",
                "Perch\u00e9 la matematica \u00e8 triste? Perch\u00e9 ha troppi problemi!"
            ],
            "argomento": "barzellette"
        },
        {
            "pattern": "come\\s*(ti)?\\s*chiami",
            "risposte": [
                "Il mio nome \u00e8 MARRtino!",
                "Puoi chiamarmi MARRtino!"
            ],
            "argomento": "generale"
        },
        {
            "pattern": "(dimmi|parlami|raccontami|sai) del colosseo",
            "risposte": [
                "Il Colosseo \u00e8 un antico anfiteatro situato nel centro di Roma.",
                "Sapevi che il Colosseo \u00e8 uno dei monumenti pi\u00f9 visitati al mondo?",
                "Il Colosseo \u00e8 stato costruito tra il 70 e l'80 d.C. durante l'Impero Romano."
            ],
            "argomento": "colosseo"
        },
        {
            "pattern": "(dimmi|parlami|raccontami|sai) paolo",
            "risposte": [
                "Paolo \u00e8 un manager di una multinazionale",
                "\u00e8 un po cosi",
                "\u00e8 prompio un rompiballe"
            ],
            "argomento": "colosseo"
        },
        {
            "pattern": "presentati",
            "risposta": "ciao ragazzi, io sono martino il robot birichino sono nato dalla collaborazione tra robotics 3d e l'universit\u00e0 la sapienza di roma. dopo anni di programmazione e miglioramenti estetici, eccomi qua! Posso parlare, cantare, ballare.  posso rispondere alle domande ed interagire con gli essere umani.",
            "argomento": "generale"
        }
    ]
}